pipxx.py
pipxx-1.11.dist-info/METADATA
pipxx-1.11.dist-info/WHEEL
pipxx-1.11.dist-info/entry_points.txt
pipxx-1.11.dist-info/top_level.txt
pipxx-1.11.dist-info/RECORD
