Metadata-Version: 2.4
Name: pipxx
Version: 1.11
Summary: Wrapper for pipx to add some minor functionality
Author-email: Mark Blakeney <mark.blakeney@bullet-systems.net>
License-Expression: GPL-3.0-or-later
Project-URL: Homepage, https://github.com/bulletmark/pipxx
Keywords: pip,pipx
Classifier: Programming Language :: Python :: 3
Requires-Python: >=3.7
